MANIFEST.in
README.txt
plonetheme.ReOrg-configure.zcml
setup.cfg
setup.py
docs/HISTORY.txt
docs/INSTALL.txt
docs/LICENSE.GPL
docs/LICENSE.txt
plonetheme/__init__.py
plonetheme.ReOrg.egg-info/PKG-INFO
plonetheme.ReOrg.egg-info/SOURCES.txt
plonetheme.ReOrg.egg-info/dependency_links.txt
plonetheme.ReOrg.egg-info/entry_points.txt
plonetheme.ReOrg.egg-info/namespace_packages.txt
plonetheme.ReOrg.egg-info/not-zip-safe
plonetheme.ReOrg.egg-info/paster_plugins.txt
plonetheme.ReOrg.egg-info/requires.txt
plonetheme.ReOrg.egg-info/top_level.txt
plonetheme/ReOrg/__init__.py
plonetheme/ReOrg/configure.zcml
plonetheme/ReOrg/profiles.zcml
plonetheme/ReOrg/setuphandlers.py
plonetheme/ReOrg/skins.zcml
plonetheme/ReOrg/tests.py
plonetheme/ReOrg/version.txt
plonetheme/ReOrg/browser/__init__.py
plonetheme/ReOrg/browser/configure.zcml
plonetheme/ReOrg/browser/interfaces.py
plonetheme/ReOrg/browser/viewlet.pt
plonetheme/ReOrg/browser/viewlets.py
plonetheme/ReOrg/browser/images/README.txt
plonetheme/ReOrg/browser/stylesheets/README.txt
plonetheme/ReOrg/browser/stylesheets/main.css
plonetheme/ReOrg/profiles/default/cssregistry.xml
plonetheme/ReOrg/profiles/default/import_steps.xml
plonetheme/ReOrg/profiles/default/jsregistry.xml
plonetheme/ReOrg/profiles/default/metadata.xml
plonetheme/ReOrg/profiles/default/plonetheme.ReOrg_various.txt
plonetheme/ReOrg/profiles/default/portlets.xml
plonetheme/ReOrg/profiles/default/skins.xml
plonetheme/ReOrg/profiles/default/viewlets.xml
plonetheme/ReOrg/profiles/uninstall/portlets.xml
plonetheme/ReOrg/profiles/uninstall/skins.xml
plonetheme/ReOrg/profiles/uninstall/viewlets.xml
plonetheme/ReOrg/skins/plonetheme_ReOrg_custom_images/CONTENT.txt
plonetheme/ReOrg/skins/plonetheme_ReOrg_custom_images/background.jpg
plonetheme/ReOrg/skins/plonetheme_ReOrg_custom_images/logo.png
plonetheme/ReOrg/skins/plonetheme_ReOrg_custom_templates/CONTENT.txt
plonetheme/ReOrg/skins/plonetheme_ReOrg_styles/CONTENT.txt
plonetheme/ReOrg/skins/plonetheme_ReOrg_styles/authoring.css.dtml
plonetheme/ReOrg/skins/plonetheme_ReOrg_styles/base.css.dtml
plonetheme/ReOrg/skins/plonetheme_ReOrg_styles/base_properties.props
plonetheme/ReOrg/skins/plonetheme_ReOrg_styles/columns.css.dtml
plonetheme/ReOrg/skins/plonetheme_ReOrg_styles/forms.css.dtml
plonetheme/ReOrg/skins/plonetheme_ReOrg_styles/public.css.dtml