Metadata-Version: 1.0
Name: plonetheme.ReOrg
Version: 1.0
Summary: Theme that reorganizes screen real-estate abd gives plone a fresh look
Home-page: http://svn.plone.org/svn/collective/
Author: David Jonas
Author-email: david@v2.nl
License: GPL
Keywords: web plone reorganize css theme zope
Platform: UNKNOWN
Classifier: Framework :: Plone
Classifier: Programming Language :: Python
Classifier: Topic :: Software Development :: Libraries :: Python Modules
